{
  "spaces": 2,
  "generator-cli": {
    "version": "5.1.0",
    "generators": {
      "v1": {
        "generatorName": "typescript-fetch",
        "glob": "openapi.transformed.json",
        "output": "./test-openapi-client",
        "additionalProperties": {
          "supportsES6": true,
          "modelPropertyNaming": "original",
          "paramNaming": "original",
          "npmName": "fastify-zod-test-openapi-client",
          "typescriptThreePlus": true,
          "generateAliasAsModel": true
        }
      }
    }
  }
}